{
  "parent": "minecraft:recipes/root",
  "criteria": {
    "has_exp_quartz_block": {
      "conditions": {
        "items": [
          {
            "items": "create_cobblemon:exp_quartz_block"
          }
        ]
      },
      "trigger": "minecraft:inventory_changed"
    },
    "has_the_recipe": {
      "conditions": {
        "recipe": "create_cobblemon:stonecutting/small_exp_quartz_tiles"
      },
      "trigger": "minecraft:recipe_unlocked"
    }
  },
  "requirements": [
    [
      "has_the_recipe",
      "has_exp_quartz_block"
    ]
  ],
  "rewards": {
    "recipes": [
      "create_cobblemon:stonecutting/small_exp_quartz_tiles"
    ]
  }
}